jugaad_aws/__init__.py
jugaad_aws/config.py
jugaad_aws/constants.py
jugaad_aws/errors.py
jugaad_aws/httpclient.py
jugaad_aws/logger.py
jugaad_aws/middleware.py
jugaad_aws/threadlocal.py
jugaad_aws/utils.py
py_jugaad_aws-0.1.3.dist-info/LICENSE
py_jugaad_aws-0.1.3.dist-info/METADATA
py_jugaad_aws-0.1.3.dist-info/WHEEL
py_jugaad_aws-0.1.3.dist-info/top_level.txt
py_jugaad_aws-0.1.3.dist-info/RECORD
