Metadata-Version: 2.1
Name: py-jugaad-aws
Version: 0.1.3
Summary: Python libraries to ease development of APIs and event driven apps for AWS serverless architecture
Author-email: Aditya Aluru <aditya.aluru@gmail.com>
License: MIT License
Project-URL: Homepage, https://github.com/adityaaluru/py-jugaad-aws
Keywords: jugaad,serverless,aws,event driven,apis,scaffolding
Classifier: License :: OSI Approved :: MIT License
Classifier: Programming Language :: Python
Classifier: Programming Language :: Python :: 3
Requires-Python: >=3.9
License-File: LICENSE
Requires-Dist: boto3
Requires-Dist: requests
